Metadata-Version: 1.0
Name: CUMSUM-Change-Point-Analytics
Version: 0.1
Summary: Change Point Detection using CUMSUM Algorithm
Home-page: UNKNOWN
Author: Michael Floyd
Author-email: mdf3039b@gmail.com
License: UNKNOWN
Platform: UNKNOWN
